globconf/ConfigSection.py
globconf/__init__.py
globconf/cfgfilestore.py
globconf/globconf.py
tests/__init__.py
tests/test_globconf.py
globconf-0.0.7.dist-info/LICENSE.md
globconf-0.0.7.dist-info/METADATA
globconf-0.0.7.dist-info/WHEEL
globconf-0.0.7.dist-info/top_level.txt
globconf-0.0.7.dist-info/RECORD
